{
    "name": "0. 總攬",
    "icon": "minecraft:writable_book",
    "category": "nen:nen",
    "pages": [
        {
            "type": "text",
            "text": "    天才、統治者、超能力者、仙人、超人...這是對世上擁有超乎尋常人能力者的稱呼。有些是天生就有，有些則是透過後天的努力取得。無論是哪種，這些人都是激發了身體的內在潛力，並能運用自如的人。這類人有一個共同的稱呼：$(9)$(l)念能力者$()。"
        },
		{
            "type": "text",
            "text": "    這些念能力者與常人不同的地方就在於：它們可以自由的操控它們自己散發出的$(9)$(l)生命能量 - 氣$()。$(br2)    幾乎所有的生命體都會散發出氣，但這些氣經常就只是流失而無法利用。一旦掌握了操控氣的技術，就能發揮出遠超出常人所及的能力。"
        },
		{
            "type": "text",
            "text": "    操控氣的技術被稱之為$(9)$(l)念$()。透過掌握念的基本技、應用技，以及持續不斷的以正確的方法修行，就可成為一名功力高強的念能力者。"
        }
    ]
}